propel_push
