Metadata-Version: 1.1
Name: Propel-Push
Version: 0.1.1
Summary: 
